nc2/Logo3.png
nc2/__init__.py
nc2/nc2.py
nc2-1.0.0.dist-info/licenses/LICENSE
nc2-1.0.0.dist-info/METADATA
nc2-1.0.0.dist-info/WHEEL
nc2-1.0.0.dist-info/entry_points.txt
nc2-1.0.0.dist-info/top_level.txt
nc2-1.0.0.dist-info/RECORD
