Metadata-Version: 2.4
Name: nc2
Version: 1.0.0
Summary: NC² NetCDF viewer
Home-page: https://github.com/rhettadam/NC2
Author: Rhett R. Adam
Author-email: rhettadambusiness@gmail.com
Classifier: Programming Language :: Python :: 3
Classifier: License :: OSI Approved :: GNU General Public License v3 (GPLv3)
Classifier: Operating System :: OS Independent
Requires-Python: >=3.6
License-File: LICENSE
Requires-Dist: numpy>=1.26.4
Requires-Dist: matplotlib>=3.8.0
Requires-Dist: netCDF4>=1.6.2
Requires-Dist: cartopy>=0.23.0
Requires-Dist: ttkbootstrap>=1.10.1
Requires-Dist: Pillow>=10.2.0
Requires-Dist: imageio>=2.33.1
Dynamic: author
Dynamic: author-email
Dynamic: classifier
Dynamic: description
Dynamic: description-content-type
Dynamic: home-page
Dynamic: license-file
Dynamic: requires-dist
Dynamic: requires-python
Dynamic: summary
